ucto.cpython-39-x86_64-linux-gnu.so
python_ucto.libs/libicudata-33bdc345.so.67.1
python_ucto.libs/libexttextcat-2-aa3651c4.0.so.0.0.0
python_ucto.libs/liblzma-712ecf44.so.5.2.5
python_ucto.libs/libicui18n-17bc7491.so.67.1
python_ucto.libs/libxml2-0d3d92a0.so.2.9.14
python_ucto.libs/libucto-15c871ab.so.6.0.0
python_ucto.libs/libstdc++-a9383cce.so.6.0.28
python_ucto.libs/libicuuc-98673c7b.so.67.1
python_ucto.libs/libgcc_s-a04fdf82.so.1
python_ucto.libs/libicuio-a3ad3dd8.so.67.1
python_ucto.libs/libfolia-f3c3227f.so.22.0.0
python_ucto.libs/libbz2-e55174b0.so.1.0.8
python_ucto.libs/libticcutils-a1021c3f.so.10.0.0
python_ucto.libs/libgomp-cd951527.so.1.0.0
python_ucto-0.6.9.data/data/sources/ucto_wrapper.pyx
python_ucto-0.6.9.dist-info/RECORD
python_ucto-0.6.9.dist-info/METADATA
python_ucto-0.6.9.dist-info/WHEEL
python_ucto-0.6.9.dist-info/top_level.txt
